{"generated": "2026-07-14", "since": "2026-07-10", "vendors": [{"name": "Am Craft Spirits", "file": "Am Craft Spirits.csv", "lines": 1}, {"name": "Bellboy Corporation", "file": "Bellboy Corporation.csv", "lines": 173}, {"name": "Bourget Imports, LLC", "file": "Bourget Imports_ LLC.csv", "lines": 1}, {"name": "Breakthru Beverage Minnesota Wine & Spirits, LLC", "file": "Breakthru Beverage Minnesota Wine _ Spirits_ LLC.csv", "lines": 146}, {"name": "Grape Beginnings, Inc.", "file": "Grape Beginnings_ Inc..csv", "lines": 5}, {"name": "Johnson Brothers - St. Paul", "file": "Johnson Brothers - St. Paul.csv", "lines": 403}, {"name": "Libation Project", "file": "Libation Project.csv", "lines": 8}, {"name": "Maverick Beverage Co., LLC - MN", "file": "Maverick Beverage Co._ LLC - MN.csv", "lines": 20}, {"name": "New France Wine Co, Inc", "file": "New France Wine Co_ Inc.csv", "lines": 15}, {"name": "Oxford Street Merchants", "file": "Oxford Street Merchants.csv", "lines": 34}, {"name": "Paustis Wine", "file": "Paustis Wine.csv", "lines": 97}, {"name": "Phillips Wine & Spirits - St. Paul", "file": "Phillips Wine _ Spirits - St. Paul.csv", "lines": 216}, {"name": "Rue 38 LLC", "file": "Rue 38 LLC.csv", "lines": 12}, {"name": "Small Lot MN", "file": "Small Lot MN.csv", "lines": 8}, {"name": "Southern Glazer's Wine & Spirits of MN", "file": "Southern Glazer_s Wine _ Spirits of MN.csv", "lines": 270}, {"name": "The Wine Company", "file": "The Wine Company.csv", "lines": 7}, {"name": "Tradition Wine & Spirits, LLC", "file": "Tradition Wine _ Spirits_ LLC.csv", "lines": 1}, {"name": "True Brands, Inc.", "file": "True Brands_ Inc..csv", "lines": 35}, {"name": "Vinocopia, Inc", "file": "Vinocopia_ Inc.csv", "lines": 11}]}